odoo10_addon_queue_job_cron-10.0.1.1.0-nspkg.pth
odoo/addons/queue_job_cron/README.rst
odoo/addons/queue_job_cron/__init__.py
odoo/addons/queue_job_cron/__manifest__.py
odoo/addons/queue_job_cron/data/data.xml
odoo/addons/queue_job_cron/i18n/queue_job_cron.pot
odoo/addons/queue_job_cron/models/__init__.py
odoo/addons/queue_job_cron/models/ir_cron.py
odoo/addons/queue_job_cron/static/description/icon.png
odoo/addons/queue_job_cron/tests/__init__.py
odoo/addons/queue_job_cron/tests/test_queue_job_cron.py
odoo/addons/queue_job_cron/views/ir_cron_view.xml
odoo10_addon_queue_job_cron-10.0.1.1.0.dist-info/METADATA
odoo10_addon_queue_job_cron-10.0.1.1.0.dist-info/WHEEL
odoo10_addon_queue_job_cron-10.0.1.1.0.dist-info/namespace_packages.txt
odoo10_addon_queue_job_cron-10.0.1.1.0.dist-info/top_level.txt
odoo10_addon_queue_job_cron-10.0.1.1.0.dist-info/RECORD
