Metadata-Version: 2.1
Name: odoo10-addon-queue-job-cron
Version: 10.0.1.1.0
Summary: Scheduled Actions as Queue Jobs
Home-page: https://github.com/OCA/queue/tree/10.0/queue_job_cron
Author: ACSONE SA/NV,Odoo Community Association (OCA)
Author-email: support@odoo-community.org
License: AGPL-3
Platform: UNKNOWN
Classifier: Programming Language :: Python
Classifier: Framework :: Odoo
Classifier: License :: OSI Approved :: GNU Affero General Public License v3
Requires-Python: ~=2.7
Requires-Dist: odoo10-addon-queue-job
Requires-Dist: odoo (<10.1dev,>=10.0)
